geopreprova1/GeoPre.py
geopreprova1/__init__.py
geopreprova1/cloud_masking.py
geopreprova1/stacking.py
geopreprova-0.1.2.dist-info/LICENSE.txt
geopreprova-0.1.2.dist-info/METADATA
geopreprova-0.1.2.dist-info/WHEEL
geopreprova-0.1.2.dist-info/top_level.txt
geopreprova-0.1.2.dist-info/RECORD
