Metadata-Version: 2.1
Name: geopreprova
Version: 0.1.2
Home-page: https://github.com/MatteoGF
Author: Matteo Gobbi Frattini, Liang Zhongyou
Author-email: matteo.gf@live.it
License: MIT
Keywords: sentinel-1 glacier velocity offset tracking remote sensing
Classifier: Development Status :: 5 - Production/Stable
Classifier: Intended Audience :: Science/Research
Classifier: Operating System :: OS Independent
Classifier: License :: OSI Approved :: MIT License
Classifier: Programming Language :: Python :: 3
Classifier: Programming Language :: Python :: 3.8
Classifier: Programming Language :: Python :: 3.9
Classifier: Programming Language :: Python :: 3.10
License-File: LICENSE.txt
Requires-Dist: geopandas>=0.10.0
Requires-Dist: snappy<4.0.0,>=2.0.0
Requires-Dist: numpy>=1.21.0
Requires-Dist: matplotlib>=3.4.0
Requires-Dist: scipy>=1.6.0
Requires-Dist: rasterio>=1.2.0
Requires-Dist: rioxarray>=0.5.0
Requires-Dist: xarray>=0.18.0
Requires-Dist: pyproj>=3.0.0
